dartboard/__init__.py
dartboard/__version__.py
dartboard/config.py
dartboard/items.py
dartboard/main.py
dartboard/upload.py
dartboard_ia-0.2.2.dist-info/entry_points.txt
dartboard_ia-0.2.2.dist-info/licenses/LICENSE
dartboard_ia-0.2.2.dist-info/METADATA
dartboard_ia-0.2.2.dist-info/WHEEL
dartboard_ia-0.2.2.dist-info/RECORD
