Metadata-Version: 2.4
Name: dartboard-ia
Version: 0.2.2
Summary: Internet Archive upload management tool
License-File: LICENSE
Author: DigitalDragon
Requires-Python: >=3.8
Classifier: Programming Language :: Python :: 3
Classifier: Programming Language :: Python :: 3.8
Classifier: Programming Language :: Python :: 3.9
Classifier: Programming Language :: Python :: 3.10
Classifier: Programming Language :: Python :: 3.11
Classifier: Programming Language :: Python :: 3.12
Classifier: Programming Language :: Python :: 3.13
Classifier: Programming Language :: Python :: 3.14
Requires-Dist: dataclasses-json
Requires-Dist: internetarchive (>=5.0.3)
Project-URL: Repository, https://github.com/DigitalDwagon/dartboard
